calcam/__init__.py
calcam/__main__.py
calcam/__version__
calcam/cadmodel.py
calcam/calibration.py
calcam/config.py
calcam/coordtransformer.py
calcam/gm.py
calcam/image_enhancement.py
calcam/io.py
calcam/misc.py
calcam/movement.py
calcam/pointpairs.py
calcam/raycast.py
calcam/render.py
calcam/builtin_image_sources/calcam_file.py
calcam/builtin_image_sources/imagefile.py
calcam/gui/__init__.py
calcam/gui/alignment_calib.py
calcam/gui/cad_edit.py
calcam/gui/core.py
calcam/gui/fitting_calib.py
calcam/gui/image_analysis.py
calcam/gui/launcher.py
calcam/gui/logo.png
calcam/gui/movement_correction.py
calcam/gui/qt_wrapper.py
calcam/gui/settings.py
calcam/gui/viewer.py
calcam/gui/virtual_calib.py
calcam/gui/vtkinteractorstyles.py
calcam/gui/icons/calcam-file.ico
calcam/gui/icons/calcam-file.png
calcam/gui/icons/calcam.ico
calcam/gui/icons/calcam.png
calcam/gui/icons/icons8.txt
calcam/gui/icons/info.png
calcam/gui/icons/new.png
calcam/gui/icons/open.png
calcam/gui/icons/save.png
calcam/gui/icons/saveas.png
calcam/gui/qt_designer_files/alignment_calib_editor.ui
calcam/gui/qt_designer_files/cad_edit.ui
calcam/gui/qt_designer_files/chessboard_image_dialog.ui
calcam/gui/qt_designer_files/fitting_calib.ui
calcam/gui/qt_designer_files/image_analyser.ui
calcam/gui/qt_designer_files/launcher.ui
calcam/gui/qt_designer_files/line_coords.ui
calcam/gui/qt_designer_files/mesh_import_settings.ui
calcam/gui/qt_designer_files/movement_corr_dialog.ui
calcam/gui/qt_designer_files/rendering_progress.ui
calcam/gui/qt_designer_files/settings.ui
calcam/gui/qt_designer_files/split_field_dialog.ui
calcam/gui/qt_designer_files/viewer.ui
calcam/gui/qt_designer_files/virtual_calib_editor.ui
calcam-2.16.2.dist-info/METADATA
calcam-2.16.2.dist-info/WHEEL
calcam-2.16.2.dist-info/entry_points.txt
calcam-2.16.2.dist-info/top_level.txt
calcam-2.16.2.dist-info/RECORD
