Metadata-Version: 2.4
Name: calcam
Version: 2.16.2
Summary: Spatial calibration tools for science & engineering camera systems.
Author-email: "Scott Silburn et. al." <scott.silburn@ukaea.uk>
License: EUPL-1.1
Project-URL: Documentation, https://euratom-software.github.io/calcam
Project-URL: Source, https://github.com/euratom-software/calcam/
Project-URL: Issue Tracker, https://github.com/euratom-software/calcam/issues
Project-URL: Zenodo, https://doi.org/10.5281/zenodo.1478554
Classifier: Development Status :: 5 - Production/Stable
Classifier: Operating System :: Microsoft :: Windows
Classifier: Operating System :: MacOS :: MacOS X
Classifier: Operating System :: POSIX :: Linux
Classifier: Environment :: Console
Classifier: Environment :: X11 Applications :: Qt
Classifier: Intended Audience :: Science/Research
Classifier: Intended Audience :: Developers
Classifier: Natural Language :: English
Classifier: Programming Language :: Python :: 3
Classifier: Topic :: Scientific/Engineering :: Physics
Classifier: Topic :: Scientific/Engineering :: Visualization
Classifier: Topic :: Scientific/Engineering :: Image Processing
Requires-Python: >=3.7
Requires-Dist: scipy
Requires-Dist: matplotlib
Requires-Dist: vtk!=9.1.*,>=7
Requires-Dist: PyQt5
Requires-Dist: opencv-python-headless
Requires-Dist: h5py
Requires-Dist: triangle
